{
  "generatedAt": "2026-03-16T23:53:35.094Z",
  "networkName": "polkadotHubTestnet",
  "polkadotHubTestnet": {
    "name": "Polkadot Hub TestNet",
    "chainId": 420420417,
    "rpcUrl": "https://eth-rpc-testnet.polkadot.io/",
    "fallbackRpcUrl": "https://services.polkadothub-rpc.com/testnet/",
    "explorerUrl": "https://blockscout-testnet.polkadot.io/",
    "faucetUrl": "https://faucet.polkadot.io/"
  },
  "roles": {
    "treasury": "0x519870b7b98a4FDc3D73cDb818634993cc942A86",
    "emergencyAdmin": "0x65712EEFD810F077c6C11Fd7c18988d3ce569C60",
    "riskAdmin": "0xE6E56B87EB128c081c59aC5a4EF8Bfe002E86944",
    "treasuryOperator": "0x519870b7b98a4FDc3D73cDb818634993cc942A86",
    "minter": "0x26fdAba4D98899b31239C1d26a98C74872bD6976"
  },
  "governance": {
    "admin": "0x65712EEFD810F077c6C11Fd7c18988d3ce569C60",
    "executionDelaySeconds": {
      "emergency": 0,
      "riskAdmin": 60,
      "treasury": 60,
      "minter": 60
    }
  },
  "config": {
    "adminDelaySeconds": 3600,
    "oracleMaxAgeSeconds": 1800,
    "oraclePriceWad": "1000000000000000000000",
    "oracle": {
      "circuitBreaker": {
        "minPriceWad": "1000000000000000000",
        "maxPriceWad": "10000000000000000000000",
        "maxPriceChangeBps": "2500"
      }
    },
    "initialLiquidity": "0",
    "pool": {
      "supplyCap": "5000000000000000000000000",
      "initialLiquidity": "0"
    },
    "core": {
      "borrowCap": "4000000000000000000000000",
      "minBorrowAmount": "100000000000000000000",
      "reserveFactorBps": "1000",
      "maxLtvBps": "7000",
      "liquidationThresholdBps": "8000",
      "liquidationBonusBps": "500"
    },
    "riskEngine": {
      "baseRateBps": "200",
      "slope1Bps": "800",
      "slope2Bps": "3000",
      "kinkBps": "8000",
      "healthyMaxLtvBps": "7500",
      "stressedMaxLtvBps": "6500",
      "healthyLiquidationThresholdBps": "8500",
      "stressedLiquidationThresholdBps": "7800",
      "staleBorrowRatePenaltyBps": "1000",
      "stressedCollateralRatioBps": "14000"
    }
  },
  "contracts": {
    "accessManager": "0x3e5a6e0c1e6cb1e7d81be67e1bb918fe89f9f68d",
    "wpas": "0xd4c0d7da71d44aa8654639256138cc96a00980ba",
    "usdc": "0x1ca879059326f4d98a42e087ef8c829024ee097f",
    "oracle": "0x35cca91b3fb1b28deb80fc827a7930f414d04c58",
    "riskEngine": "0x1e6903a816be0bc013291bbed547df45bdc9e86c",
    "marketRegistry": "0xb9ac70cea8e171908c885ac0ca2aec122598d322",
    "governanceToken": "0x35922553c33360e3e7f375a9e1bedc686567e184",
    "governor": "0xc500a9e8762412b933ad21eec059cd837995a426",
    "governanceTimelock": "0xb4dd0c82a6450c1e0321b730695dc06e8a854102",
    "debtPool": "0xdab6cca9e5581fcb9df1a97282bd6d5f768f26c6",
    "lendingEngine": "0xb34267586877e32aa001f37371364283ac22dac7",
    "lendingRouter": "0xD960c11A2c06faC6c7cb2eEE9B419EE5DF1e5F6E",
    "pvmDeterministicRiskModel": "0x1e6903a816be0bc013291bbed547df45bdc9e86c"
  }
}